gaarf_io/__init__.py
gaarf_io/formatter.py
gaarf_io/reader.py
gaarf_io/writer.py
gaarf_io/writers/__init__.py
gaarf_io/writers/abs_writer.py
gaarf_io/writers/bigquery_writer.py
gaarf_io/writers/console_writer.py
gaarf_io/writers/csv_writer.py
gaarf_io/writers/file_writer.py
gaarf_io/writers/json_writer.py
gaarf_io/writers/null_writer.py
gaarf_io/writers/sheets_writer.py
gaarf_io/writers/sqldb_writer.py
gaarf_io-0.0.1.dist-info/METADATA
gaarf_io-0.0.1.dist-info/WHEEL
gaarf_io-0.0.1.dist-info/top_level.txt
gaarf_io-0.0.1.dist-info/RECORD
