Metadata-Version: 2.1
Name: gaarf-io
Version: 0.0.1
Summary: Handles reading queries and writing GaarfReport from gaarf-core package
Author-email: "Google Inc. (gTech gPS CSE team)" <no-reply@google.com>
License: Apache 2.0
Classifier: Programming Language :: Python :: 3 :: Only
Classifier: Programming Language :: Python :: 3.8
Classifier: Programming Language :: Python :: 3.9
Classifier: Programming Language :: Python :: 3.10
Classifier: Programming Language :: Python :: 3.11
Classifier: Programming Language :: Python :: 3.12
Classifier: Intended Audience :: Developers
Classifier: Topic :: Software Development :: Libraries :: Python Modules
Classifier: Operating System :: OS Independent
Classifier: License :: OSI Approved :: Apache Software License
Requires-Python: >=3.8
Requires-Dist: gaarf-core
Requires-Dist: smart-open
Requires-Dist: rich
Provides-Extra: all
Requires-Dist: gaarf-io[bq,sheets,sqlalchemy] ; extra == 'all'
Provides-Extra: bq
Requires-Dist: google-cloud-bigquery ; extra == 'bq'
Requires-Dist: pandas ; extra == 'bq'
Requires-Dist: smart-open[gcs] ; extra == 'bq'
Provides-Extra: sheets
Requires-Dist: gspread ; extra == 'sheets'
Provides-Extra: sqlalchemy
Requires-Dist: sqlalchemy ; extra == 'sqlalchemy'
Requires-Dist: pandas ; extra == 'sqlalchemy'
